edupils/__init__.py
edupils/constantes.py
edupils/desafios/__init__.py
edupils/desafios/bejeweled.py
edupils/desafios/cinematica.py
edupils/desafios/gude.py
edupils/desafios/labirinto.py
edupils/desafios/p5.py
edupils/desafios/tartaruga.py
edupils/desenho/__init__.py
edupils/desenho/desenho.py
edupils/desenho/formatar-btns.py
edupils/desenho/painel.py
edupils/fisica/__init__.py
edupils/fisica/forcas.py
edupils/fisica/grandezas.py
edupils/fisica/motor.py
edupils/fisica/vetor.py
edupils/imagem/__init__.py
edupils/imagem/image_handler.py
edupils/sons/__init__.py
edupils/sons/audio_handler.py
edupils-0.1.29.dist-info/licenses/LICENSE
edupils-0.1.29.dist-info/METADATA
edupils-0.1.29.dist-info/WHEEL
edupils-0.1.29.dist-info/top_level.txt
edupils-0.1.29.dist-info/RECORD
