Metadata-Version: 2.4
Name: edupils
Version: 0.1.29
Summary: A collection of educational tools for Python
Home-page: https://github.com/georgesms/edupils
Author: Georges Spyrides
Author-email: georgesmss@gmail.com
License: MIT
Keywords: python education highschool pyodide
License-File: LICENSE
Dynamic: author
Dynamic: author-email
Dynamic: description
Dynamic: description-content-type
Dynamic: home-page
Dynamic: keywords
Dynamic: license
Dynamic: license-file
Dynamic: summary
